xpresso/__init__.py
xpresso/_utils/__init__.py
xpresso/_utils/asgi.py
xpresso/_utils/endpoint_dependent.py
xpresso/_utils/overrides.py
xpresso/_utils/pydantic_utils.py
xpresso/_utils/routing.py
xpresso/_utils/schemas.py
xpresso/_utils/scope_resolver.py
xpresso/_utils/typing.py
xpresso/applications.py
xpresso/background.py
xpresso/binders/__init__.py
xpresso/binders/_binders/__init__.py
xpresso/binders/_binders/cookie_params.py
xpresso/binders/_binders/file_body.py
xpresso/binders/_binders/form_body.py
xpresso/binders/_binders/formencoded_parsing.py
xpresso/binders/_binders/grouped.py
xpresso/binders/_binders/header_params.py
xpresso/binders/_binders/json_body.py
xpresso/binders/_binders/media_type_validator.py
xpresso/binders/_binders/param_openapi.py
xpresso/binders/_binders/path_params.py
xpresso/binders/_binders/pydantic_validators.py
xpresso/binders/_binders/query_params.py
xpresso/binders/_binders/union.py
xpresso/binders/_binders/utils.py
xpresso/binders/api.py
xpresso/binders/dependents.py
xpresso/bodies.py
xpresso/config.py
xpresso/datastructures.py
xpresso/dependencies/__init__.py
xpresso/dependencies/_dependencies.py
xpresso/encoders.py
xpresso/exception_handlers.py
xpresso/exceptions.py
xpresso/middleware/__init__.py
xpresso/middleware/cors.py
xpresso/middleware/exceptions.py
xpresso/middleware/gzip.py
xpresso/middleware/httpsredirect.py
xpresso/middleware/trustedhost.py
xpresso/openapi/__init__.py
xpresso/openapi/_builder.py
xpresso/openapi/_constants.py
xpresso/openapi/_html.py
xpresso/openapi/_utils.py
xpresso/openapi/models.py
xpresso/parameters.py
xpresso/py.typed
xpresso/requests.py
xpresso/responses.py
xpresso/routing/__init__.py
xpresso/routing/host.py
xpresso/routing/mount.py
xpresso/routing/operation.py
xpresso/routing/pathitem.py
xpresso/routing/router.py
xpresso/routing/websockets.py
xpresso/staticfiles.py
xpresso/testclient.py
xpresso/typing.py
xpresso/websockets.py
xpresso-0.46.0.dist-info/LICENSE.txt
xpresso-0.46.0.dist-info/WHEEL
xpresso-0.46.0.dist-info/METADATA
xpresso-0.46.0.dist-info/RECORD
