Metadata-Version: 2.1
Name: xpresso
Version: 0.46.0
Summary: A developer centric, performant Python web framework
Home-page: https://github.com/adriangb/xpresso
License: MIT
Keywords: web-framework,http,openapi
Author: Adrian Garcia Badaracco
Author-email: adrian@adriangb.com
Requires-Python: >=3.7,<4
Classifier: Development Status :: 3 - Alpha
Classifier: Environment :: Web Environment
Classifier: Framework :: AsyncIO
Classifier: Intended Audience :: Developers
Classifier: Intended Audience :: Information Technology
Classifier: Intended Audience :: System Administrators
Classifier: License :: OSI Approved :: MIT License
Classifier: Operating System :: OS Independent
Classifier: Programming Language :: Python
Classifier: Programming Language :: Python :: 3
Classifier: Programming Language :: Python :: 3 :: Only
Classifier: Programming Language :: Python :: 3.10
Classifier: Programming Language :: Python :: 3.7
Classifier: Programming Language :: Python :: 3.8
Classifier: Programming Language :: Python :: 3.9
Classifier: Topic :: Internet
Classifier: Topic :: Internet :: WWW/HTTP
Classifier: Topic :: Internet :: WWW/HTTP :: HTTP Servers
Classifier: Topic :: Software Development
Classifier: Topic :: Software Development :: Libraries
Classifier: Topic :: Software Development :: Libraries :: Application Frameworks
Classifier: Topic :: Software Development :: Libraries :: Python Modules
Classifier: Typing :: Typed
Requires-Dist: anyio (>=3.4.0,<5)
Requires-Dist: di (==0.73.0)
Requires-Dist: pydantic (>=1.10.2,<2.0.0)
Requires-Dist: starlette (>=0.21.0,<1)
Requires-Dist: typing-extensions (>=3); python_version < "3.9"
Project-URL: Documentation, https://www.xpresso-api.dev
Project-URL: Repository, https://github.com/adriangb/xpresso
